bits/__init__.py
bits/google/__init__.py
bits/google/models/__init__.py
bits/google/models/billing_account.py
bits/google/models/invoice.py
bits/google/services/__init__.py
bits/google/services/base.py
bits/google/services/bigquery.py
bits/google/services/billing.py
bits/google/services/budgets.py
bits/google/services/cai.py
bits/google/services/calendar.py
bits/google/services/cloudbuild.py
bits/google/services/cloudprint.py
bits/google/services/cloudsearch.py
bits/google/services/compute.py
bits/google/services/crm.py
bits/google/services/datastore.py
bits/google/services/directory.py
bits/google/services/dns.py
bits/google/services/drive.py
bits/google/services/firestore.py
bits/google/services/gmail.py
bits/google/services/groupssettings.py
bits/google/services/iam.py
bits/google/services/iamcredentials.py
bits/google/services/identity.py
bits/google/services/labelmanager.py
bits/google/services/licensing.py
bits/google/services/people.py
bits/google/services/privatecatalog.py
bits/google/services/pubsub.py
bits/google/services/recommender.py
bits/google/services/reports.py
bits/google/services/resourcesearch.py
bits/google/services/secretmanager.py
bits/google/services/securitycenter.py
bits/google/services/serviceusage.py
bits/google/services/sheets.py
bits/google/services/sourcerepo.py
bits/google/services/sql.py
bits/google/services/storage.py
bits/google/services/vault.py
bits_google-2.0.0.dist-info/METADATA
bits_google-2.0.0.dist-info/WHEEL
bits_google-2.0.0.dist-info/RECORD
